terrajinja/imports/kubectl/__init__.py
terrajinja/imports/kubectl/py.typed
terrajinja/imports/kubectl/_jsii/__init__.py
terrajinja/imports/kubectl/_jsii/kubectl@0.0.0.jsii.tgz
terrajinja/imports/kubectl/data_kubectl_file_documents/__init__.py
terrajinja/imports/kubectl/data_kubectl_filename_list/__init__.py
terrajinja/imports/kubectl/data_kubectl_path_documents/__init__.py
terrajinja/imports/kubectl/data_kubectl_server_version/__init__.py
terrajinja/imports/kubectl/manifest/__init__.py
terrajinja/imports/kubectl/provider/__init__.py
terrajinja/imports/kubectl/server_version/__init__.py
terrajinja_imports_kubectl-2.0.4.dist-info/LICENSE
terrajinja_imports_kubectl-2.0.4.dist-info/METADATA
terrajinja_imports_kubectl-2.0.4.dist-info/WHEEL
terrajinja_imports_kubectl-2.0.4.dist-info/top_level.txt
terrajinja_imports_kubectl-2.0.4.dist-info/RECORD
